example_pkg/__init__.py
example_pkg/test.py
example_pkg/sec_example_pkg/__init__.py
woshinidie002-0.0.1.dist-info/METADATA
woshinidie002-0.0.1.dist-info/WHEEL
woshinidie002-0.0.1.dist-info/top_level.txt
woshinidie002-0.0.1.dist-info/RECORD
