Metadata-Version: 2.1
Name: woshinidie002
Version: 0.0.1
Summary: A  module for test
Home-page: https://github.com/SengeNB/OliverSen
Author: Sen
Author-email: zhangsen2001@gmail.com
License: UNKNOWN
Platform: UNKNOWN
